advanced_math/__init__.py
advanced_math/abs_equation.py
advanced_math/difficult_equation.py
advanced_math/fraction.py
advanced_math/integral_expression.py
advanced_math/misc.py
advanced_math/simple_equation.py
advanced_math/test.py
advancedmath/__init__.py
advancedmath/abs_equation.py
advancedmath/difficult_equation.py
advancedmath/fraction.py
advancedmath/integral_expression.py
advancedmath/misc.py
advancedmath/simple_equation.py
advancedmath/test.py
advancedmaths-1.0.0b1.dist-info/METADATA
advancedmaths-1.0.0b1.dist-info/WHEEL
advancedmaths-1.0.0b1.dist-info/top_level.txt
advancedmaths-1.0.0b1.dist-info/RECORD
