Metadata-Version: 2.1
Name: advancedmaths
Version: 1.0.0b1
Summary: A module to calculate math problems.
Home-page: https://github.com/CokeStudios/AdvancedMath
Author: JamesJ
Author-email: GGJamesQQ@yeah.net
License: UNKNOWN
Platform: UNKNOWN
Classifier: Programming Language :: Python
Classifier: License :: OSI Approved :: MIT License
Classifier: Development Status :: 4 - Beta
Classifier: Topic :: Scientific/Engineering :: Mathematics
Requires-Python: >=3.6.0
